plingo/__init__.py
plingo/meta_problog.py
plingo/opt.py
plingo/plingo_app.py
plingo/plog.py
plingo/probability.py
plingo/query.py
plingo/transformer.py
plingo-1.1.0.dist-info/LICENSE
plingo-1.1.0.dist-info/METADATA
plingo-1.1.0.dist-info/WHEEL
plingo-1.1.0.dist-info/entry_points.txt
plingo-1.1.0.dist-info/top_level.txt
plingo-1.1.0.dist-info/RECORD
