Metadata-Version: 2.1
Name: plingo
Version: 1.1.0
Summary: Probabilistic extension for clingo
Home-page: https://github.com/nrueh/plingo/
Author: Nicolas Rühling
Author-email: nruehling@uni-potsdam.de
License: MIT
License-File: LICENSE
Requires-Dist: clingo (>=5.5)
